republictime/__init__.py
republictime/apps.py
republictime/urls.py
republictime/migrations/__init__.py
republictime/templates/djangoadmin/republictime/homepage_view.html
republictime/views/HomePageView.py
republictime/views/__init__.py
republictime-2.2.0.dist-info/License
republictime-2.2.0.dist-info/METADATA
republictime-2.2.0.dist-info/WHEEL
republictime-2.2.0.dist-info/top_level.txt
republictime-2.2.0.dist-info/RECORD
